Compression/__init__.py
Compression/PyTorch/__init__.py
Compression/PyTorch/analysis/LogisticRegression.py
Compression/PyTorch/analysis/__init__.py
Compression/PyTorch/analysis/disease_nn.py
Compression/PyTorch/nlp_llm/__init__.py
Compression/PyTorch/nlp_llm/finetune1.py
Compression/PyTorch/nlp_llm/gen_train_1.py
Compression/PyTorch/nlp_llm/merge.py
Compression/PyTorch/nlp_llm/merge_with_predict1.py
Compression/PyTorch/nlp_llm/qwen.py
Compression/PyTorch/prune/GraphPrune.py
Compression/PyTorch/prune/__init__.py
Compression/PyTorch/prune/Weight/__init__.py
Compression/PyTorch/prune/Weight/compute_bn.py
Compression/PyTorch/prune/Weight/compute_conv.py
Compression/PyTorch/prune/data_prune/__init__.py
Compression/PyTorch/prune/data_prune/auto_dependency.py
Compression/PyTorch/prune/data_prune/conv_km.py
Compression/PyTorch/prune/one_shot/__init__.py
Compression/PyTorch/prune/one_shot/fpgm_conv_prune.py
Compression/PyTorch/prune/one_shot/ln_bn_prune.py
Compression/PyTorch/prune/one_shot/ln_conv_prune.py
Compression/PyTorch/vision/__init__.py
Compression/PyTorch/vision/deepv3.py
Compression/PyTorch/vision/unet.py
Compression/PyTorch/vision/val.py
Compression/PyTorch/vision/maskrcnn/__init__.py
Compression/PyTorch/vision/maskrcnn/json2coco.py
Compression/PyTorch/vision/maskrcnn/plot_mask_on_ori.py
Compression/PyTorch/vision/maskrcnn/predict_carlar.py
Compression/PyTorch/vision/maskrcnn/train.py
Compression/PyTorch/vision/maskrcnn/pytorch_mask_rcnn/__init__.py
Compression/PyTorch/vision/maskrcnn/pytorch_mask_rcnn/engine.py
Compression/PyTorch/vision/maskrcnn/pytorch_mask_rcnn/gpu.py
Compression/PyTorch/vision/maskrcnn/pytorch_mask_rcnn/utils.py
Compression/PyTorch/vision/maskrcnn/pytorch_mask_rcnn/visualizer.py
Compression/PyTorch/vision/maskrcnn/pytorch_mask_rcnn/datasets/__init__.py
Compression/PyTorch/vision/maskrcnn/pytorch_mask_rcnn/datasets/coco_dataset.py
Compression/PyTorch/vision/maskrcnn/pytorch_mask_rcnn/datasets/coco_eval.py
ModelCompression-0.1.6.dist-info/METADATA
ModelCompression-0.1.6.dist-info/WHEEL
ModelCompression-0.1.6.dist-info/top_level.txt
ModelCompression-0.1.6.dist-info/RECORD
