Metadata-Version: 2.1
Name: ModelCompression
Version: 0.1.6
Summary: Neural Network Compression
Home-page: UNKNOWN
Author: AI Team
Author-email: 710783765@qq.com
License: MIT
Platform: UNKNOWN
Requires-Python: >=3.6.2
Requires-Dist: thop
